{
    "SOL/USDT": {
        "v39": {
            "net_profit_pct": 0.2286475591649264,
            "win_rate": 50.0,
            "total_trades": 4
        },
        "v40": {
            "net_profit_pct": 1.7028860128728638,
            "win_rate": 100.0,
            "total_trades": 1
        }
    },
    "NEAR/USDT": {
        "v39": {
            "net_profit_pct": -6.890632028893355,
            "win_rate": 0.0,
            "total_trades": 6
        },
        "v40": {
            "net_profit_pct": 0,
            "win_rate": 0,
            "total_trades": 0
        }
    },
    "BTC/USDT": {
        "v39": {
            "net_profit_pct": -3.818800631712781,
            "win_rate": 14.285714285714285,
            "total_trades": 7
        },
        "v40": {
            "net_profit_pct": 0,
            "win_rate": 0,
            "total_trades": 0
        }
    }
}